{
  "id": "cost-optimization",
  "slug": "construction-cost-optimization",
  "title": "Construction Cost Optimization Strategies",
  "description": "Effective ways to reduce construction costs without sacrificing quality.",
  "publishDate": "2025-02-10T09:15:00Z",
  "imageUrl": "/demos/projects-interface.png",
  "categories": [
    {
      "slug": "cost-management",
      "name": "Cost Management"
    }
  ],
  "content": "\n      <p>Construction cost optimization is crucial for maintaining profitability in today's competitive market. Here are proven strategies that can help reduce expenses while maintaining quality standards.</p>\n\n      <h2>1. Strategic Planning and Design Optimization</h2>\n      <p>Effective cost management begins during the planning phase. Value engineering techniques can identify opportunities to reduce costs while maintaining functionality.</p>\n\n      <h2>2. Material Selection and Procurement</h2>\n      <p>Strategic sourcing and bulk purchasing can significantly reduce material costs. Consider alternative materials that offer similar performance at lower price points.</p>\n\n      <h2>3. Labor Efficiency and Training</h2>\n      <p>Investing in workforce training and process optimization can improve productivity and reduce labor costs over time.</p>\n\n      <h2>4. Technology Integration</h2>\n      <p>Construction management software and digital tools can help identify cost-saving opportunities and improve project efficiency.</p>\n\n      <p>Remember, cost optimization should never compromise safety or quality. The goal is to build more efficiently, not cut corners.</p>\n    ",
  "author": {
    "name": "Cost Management Specialists"
  }
}